crses/__init__.py
crses/crses.py
crses-1.0.5.dist-info/LICENSE
crses-1.0.5.dist-info/METADATA
crses-1.0.5.dist-info/WHEEL
crses-1.0.5.dist-info/top_level.txt
crses-1.0.5.dist-info/RECORD
